{
    "version": "0.87.100",
    "architecture": {
        "64bit": {
            "url": "https://github.com/slingdata-io/sling-cli/releases/download/v0.87.100/sling_0.87.100_windows_amd64.tar.gz",
            "bin": [
                "sling.exe"
            ],
            "hash": "567851f7645e0d890c288bee888b8c6192a33a0e7a25b72178d8f7a50d5141d5"
        }
    },
    "homepage": "https:/slingdata.io/",
    "description": "Data Integration made simple, from the command line. Extract and load data from popular data sources to destinations with high performance and ease."
}