{
    "version": "0.87.77",
    "architecture": {
        "64bit": {
            "url": "https://ocral.nyc3.digitaloceanspaces.com/slingdata.io/dist/0.87.77/sling_0.87.77_Windows_x86_64.tar.gz",
            "bin": [
                "sling.exe"
            ],
            "hash": "9921b7021f5d2938cf952b3d092c8d14e037be0737b52fb36f3aa6ee43cdda2f"
        }
    },
    "homepage": "https:/slingdata.io/en/cli",
    "description": "Data Integration made simple, from the command line. Extract and load data from popular data sources to destinations with high performance and ease."
}